pyppesnap/__init__.py
pyppesnap/cli.py
pyppesnap/snapshot.py
PyppeSnap-1.0.6.dist-info/LICENSE
PyppeSnap-1.0.6.dist-info/METADATA
PyppeSnap-1.0.6.dist-info/WHEEL
PyppeSnap-1.0.6.dist-info/entry_points.txt
PyppeSnap-1.0.6.dist-info/top_level.txt
PyppeSnap-1.0.6.dist-info/RECORD
