Metadata-Version: 2.1
Name: PyppeSnap
Version: 1.0.6
Summary: Get a snapshot from a website by using Pyppeteer.
Home-page: https://github.com/natlee/PyppeSnap
Author: Nat Lee
Author-email: natlee.work@gmail.com
Project-URL: Documentation, https://github.com/natlee/PyppeSnap
Project-URL: Bug Reports, https://github.com/natlee/PyppeSnap/issues
Project-URL: Source Code, https://github.com/natlee/PyppeSnap
Keywords: pyppeteer,snapshot
Classifier: Development Status :: 5 - Production/Stable
Classifier: Intended Audience :: Developers
Classifier: Topic :: Software Development :: Build Tools
Classifier: Programming Language :: Python :: 3
Classifier: Programming Language :: Python :: 3.7
Classifier: Programming Language :: Python :: 3.8
Classifier: Programming Language :: Python :: 3.9
Classifier: Programming Language :: Python :: 3 :: Only
Classifier: License :: OSI Approved :: MIT License
Classifier: Operating System :: OS Independent
Requires-Python: >=3.7
License-File: LICENSE
Requires-Dist: websockets (==8.1)
Requires-Dist: pyee (==6.0.0)
Requires-Dist: pyppeteer (>=0.0.25)
Provides-Extra: dev
Requires-Dist: check-manifest ; extra == 'dev'
